MANIFEST.in
README.md
setup.py
pyautoreload/__init__.py
pyautoreload.egg-info/PKG-INFO
pyautoreload.egg-info/SOURCES.txt
pyautoreload.egg-info/dependency_links.txt
pyautoreload.egg-info/requires.txt
pyautoreload.egg-info/top_level.txt